{
    "data": [
        {
            "advertiser": {
                "id": "61015687",
                "description": "PT Hana Fashion Indonesia"
            },
            "bulletPoints": [
                "BPJS KESEHATAN & KETENAGAKERJAAN",
                "THR",
                "Hana Cafe, Hana Salon and Hana Massage"
            ],
            "branding": {
                "serpLogoUrl": "https://bx-branding-gateway.cloud.seek.com.au/d0e3612c-119d-4eb8-9eb2-d25dd275abfc.1/serpLogo"
            },
            "classifications": [
                {
                    "classification": {
                        "id": "6092",
                        "description": "Manufaktur, Transportasi & Logistik"
                    },
                    "subclassification": {
                        "id": "6104",
                        "description": "Pembuatan Pola & Teknisi Garmen"
                    }
                }
            ],
            "companyName": "Hana Fashion Indonesia",
            "companyProfileStructuredDataId": 433238,
            "displayStyle": {
                "search": "A"
            },
            "displayType": "standout",
            "id": "79997402",
            "isFeatured": false,
            "listingDate": "2024-11-06T05:56:00Z",
            "listingDateDisplay": "18 hari yang lalu",
            "locations": [
                {
                    "label": "Jakarta Barat, Jakarta Raya",
                    "countryCode": "ID",
                    "seoHierarchy": [
                        {
                            "contextualName": "Jakarta Barat Jakarta Raya"
                        },
                        {
                            "contextualName": "Jakarta Raya"
                        }
                    ]
                }
            ],
            "roleId": "patternmaker",
            "salaryLabel": "Rp 5.000.000 – Rp 7.000.000 per month",
            "solMetadata": {
                "searchRequestToken": "f0f542dd-ece5-452d-a708-20dc4f799947",
                "token": "0~f0f542dd-ece5-452d-a708-20dc4f799947",
                "jobId": "79997402",
                "section": "MAIN",
                "sectionRank": 1121,
                "jobAdType": "ORGANIC",
                "tags": {
                    "mordor__flights": "mordor_510",
                    "mordor__s": "1"
                }
            },
            "teaser": "Handling the pattern making in our company with optitex 21 software",
            "title": "Pattern Maker (Garment)",
            "tracking": "ewogICJ0b2tlbiI6ICI1YzYyYTg1Mi01MzJmLTQ5ZmUtYmM2ZS02OGRkOWE3ZDY2MGJfMSIKfQ==",
            "workTypes": [
                "Full time"
            ],
            "workArrangements": {
                "data": [
                    {
                        "id": "1",
                        "label": {
                            "text": "Kantor"
                        }
                    }
                ]
            }
        },
        {
            "advertiser": {
                "id": "60338616",
                "description": "PT. Metrodata Electronics, Tbk"
            },
            "bulletPoints": [],
            "branding": {
                "serpLogoUrl": "https://bx-branding-gateway.cloud.seek.com.au/f56b77a1-d13b-4f3a-9fbb-05cef9b13995.2/serpLogo"
            },
            "classifications": [
                {
                    "classification": {
                        "id": "6281",
                        "description": "Teknologi Informasi & Komunikasi"
                    },
                    "subclassification": {
                        "id": "6291",
                        "description": "Meja Bantuan & Dukungan IT"
                    }
                }
            ],
            "companyName": "Metrodata",
            "companyProfileStructuredDataId": 414113,
            "displayType": "standard",
            "id": "80263943",
            "isFeatured": false,
            "listingDate": "2024-11-19T02:38:48Z",
            "listingDateDisplay": "5 hari yang lalu",
            "locations": [
                {
                    "label": "Jakarta Pusat, Jakarta Raya",
                    "countryCode": "ID",
                    "seoHierarchy": [
                        {
                            "contextualName": "Jakarta Pusat Jakarta Raya"
                        },
                        {
                            "contextualName": "Jakarta Raya"
                        }
                    ]
                }
            ],
            "roleId": "information-technology-support",
            "salaryLabel": "",
            "solMetadata": {
                "searchRequestToken": "f0f542dd-ece5-452d-a708-20dc4f799947",
                "token": "0~f0f542dd-ece5-452d-a708-20dc4f799947",
                "jobId": "80263943",
                "section": "MAIN",
                "sectionRank": 1122,
                "jobAdType": "ORGANIC",
                "tags": {
                    "mordor__flights": "mordor_510",
                    "mordor__s": "1"
                }
            },
            "teaser": "Support relating with the end user support of Information Technology matters.",
            "title": "IT SUPPORT",
            "tracking": "ewogICJ0b2tlbiI6ICI1YzYyYTg1Mi01MzJmLTQ5ZmUtYmM2ZS02OGRkOWE3ZDY2MGJfMiIKfQ==",
            "workTypes": [
                "Kontrak"
            ],
            "workArrangements": {
                "data": [
                    {
                        "id": "1",
                        "label": {
                            "text": "Kantor"
                        }
                    }
                ]
            }
        },
        {
            "advertiser": {
                "id": "60219671",
                "description": "PT SGMW Motor Indonesia"
            },
            "bulletPoints": [],
            "branding": {
                "serpLogoUrl": "https://bx-branding-gateway.cloud.seek.com.au/5b12e3d8-a111-46d3-b316-8ade79829f6d.1/serpLogo"
            },
            "classifications": [
                {
                    "classification": {
                        "id": "1209",
                        "description": "Teknik"
                    },
                    "subclassification": {
                        "id": "6035",
                        "description": "Teknik Mesin"
                    }
                }
            ],
            "companyName": "SGMW Motor Indonesia",
            "companyProfileStructuredDataId": 436946,
            "displayStyle": {
                "search": "A"
            },
            "displayType": "standout",
            "id": "80228238",
            "isFeatured": false,
            "listingDate": "2024-11-17T11:02:07Z",
            "listingDateDisplay": "6 hari yang lalu",
            "locations": [
                {
                    "label": "Cikarang Pusat, Jawa Barat",
                    "countryCode": "ID",
                    "seoHierarchy": [
                        {
                            "contextualName": "Cikarang Pusat Jawa Barat"
                        },
                        {
                            "contextualName": "Jawa Barat"
                        }
                    ]
                }
            ],
            "roleId": "manufacturing-engineer",
            "salaryLabel": "",
            "solMetadata": {
                "searchRequestToken": "f0f542dd-ece5-452d-a708-20dc4f799947",
                "token": "0~f0f542dd-ece5-452d-a708-20dc4f799947",
                "jobId": "80228238",
                "section": "MAIN",
                "sectionRank": 1123,
                "jobAdType": "ORGANIC",
                "tags": {
                    "mordor__flights": "mordor_510",
                    "mordor__s": "1"
                }
            },
            "teaser": "Bachelor Degree in Engineering who has experience in manufacturing especially for welding process.",
            "title": "Manufacturing Engineer",
            "tracking": "ewogICJ0b2tlbiI6ICI1YzYyYTg1Mi01MzJmLTQ5ZmUtYmM2ZS02OGRkOWE3ZDY2MGJfMyIKfQ==",
            "workTypes": [
                "Full time"
            ],
            "workArrangements": {
                "data": [
                    {
                        "id": "1",
                        "label": {
                            "text": "Kantor"
                        }
                    }
                ]
            }
        },
        {
            "advertiser": {
                "id": "60857441",
                "description": "PT Putraduta Buanasentosa"
            },
            "bulletPoints": [],
            "branding": {
                "serpLogoUrl": "https://bx-branding-gateway.cloud.seek.com.au/1c5f07c9-8a95-46a0-b387-afd0c5227a13.2/serpLogo"
            },
            "classifications": [
                {
                    "classification": {
                        "id": "6362",
                        "description": "Penjualan"
                    },
                    "subclassification": {
                        "id": "6367",
                        "description": "Koordinator Penjualan"
                    }
                }
            ],
            "companyName": "Putraduta Buanasentosa",
            "companyProfileStructuredDataId": 436302,
            "displayType": "standard",
            "id": "80200449",
            "isFeatured": false,
            "listingDate": "2024-11-15T02:48:13Z",
            "listingDateDisplay": "9 hari yang lalu",
            "locations": [
                {
                    "label": "Jawa Tengah",
                    "countryCode": "ID",
                    "seoHierarchy": [
                        {
                            "contextualName": "Jawa Tengah"
                        }
                    ]
                }
            ],
            "roleId": "head-of-department",
            "salaryLabel": "Rp 5.900.000 – Rp 6.500.000 per month",
            "solMetadata": {
                "searchRequestToken": "f0f542dd-ece5-452d-a708-20dc4f799947",
                "token": "0~f0f542dd-ece5-452d-a708-20dc4f799947",
                "jobId": "80200449",
                "section": "MAIN",
                "sectionRank": 1124,
                "jobAdType": "ORGANIC",
                "tags": {
                    "mordor__flights": "mordor_510",
                    "mordor__s": "1"
                }
            },
            "teaser": "Bersedia di rotasi ke seluruh cabang Indoarsip (Medan, Jakarta, Bandung, Semarang, Klaten, Surabaya, Makassar)",
            "title": "Sales Marketing Section Head",
            "tracking": "ewogICJ0b2tlbiI6ICI1YzYyYTg1Mi01MzJmLTQ5ZmUtYmM2ZS02OGRkOWE3ZDY2MGJfNCIKfQ==",
            "workTypes": [
                "Full time"
            ],
            "workArrangements": {
                "data": [
                    {
                        "id": "1",
                        "label": {
                            "text": "Kantor"
                        }
                    }
                ]
            }
        },
        {
            "advertiser": {
                "id": "60892111",
                "description": "PT China Comservice Indonesia"
            },
            "bulletPoints": [],
            "branding": {
                "serpLogoUrl": "https://bx-branding-gateway.cloud.seek.com.au/7d8e547d-4ac3-4331-80ba-53f9e838e05b.1/serpLogo"
            },
            "classifications": [
                {
                    "classification": {
                        "id": "1209",
                        "description": "Teknik"
                    },
                    "subclassification": {
                        "id": "6028",
                        "description": "Teknik Elektro/Elektronik"
                    }
                }
            ],
            "companyName": "China Comservice Indonesia",
            "companyProfileStructuredDataId": 431562,
            "displayStyle": {
                "search": "A"
            },
            "displayType": "standout",
            "id": "80172044",
            "isFeatured": false,
            "listingDate": "2024-11-14T02:10:09Z",
            "listingDateDisplay": "10 hari yang lalu",
            "locations": [
                {
                    "label": "Jakarta Pusat, Jakarta Raya",
                    "countryCode": "ID",
                    "seoHierarchy": [
                        {
                            "contextualName": "Jakarta Pusat Jakarta Raya"
                        },
                        {
                            "contextualName": "Jakarta Raya"
                        }
                    ]
                }
            ],
            "roleId": "electrical-engineer",
            "salaryLabel": "Rp 6.700.000 – Rp 10.000.000 per month",
            "solMetadata": {
                "searchRequestToken": "f0f542dd-ece5-452d-a708-20dc4f799947",
                "token": "0~f0f542dd-ece5-452d-a708-20dc4f799947",
                "jobId": "80172044",
                "section": "MAIN",
                "sectionRank": 1125,
                "jobAdType": "ORGANIC",
                "tags": {
                    "mordor__flights": "mordor_510",
                    "mordor__s": "1"
                }
            },
            "teaser": "UPS (Uninterruptible Power Supplies), generators, switchgear, transformers, power distribution units, and backup power systems.",
            "title": "DATA CENTER ELECTRICAL ENGINEER",
            "tracking": "ewogICJ0b2tlbiI6ICI1YzYyYTg1Mi01MzJmLTQ5ZmUtYmM2ZS02OGRkOWE3ZDY2MGJfNSIKfQ==",
            "workTypes": [
                "Full time"
            ],
            "workArrangements": {
                "data": [
                    {
                        "id": "1",
                        "label": {
                            "text": "Kantor"
                        }
                    }
                ]
            }
        },
        {
            "advertiser": {
                "id": "62137526",
                "description": "PT Jensen Group Bali"
            },
            "bulletPoints": [
                "A collaborative and professional work environment.",
                "Competitive salary and comprehensive benefits package.",
                "Opportunities for professional development and career advancement."
            ],
            "branding": {
                "serpLogoUrl": "https://bx-branding-gateway.cloud.seek.com.au/aabdbf54-c34a-45de-8a70-68856c651417.1/serpLogo"
            },
            "classifications": [
                {
                    "classification": {
                        "id": "6263",
                        "description": "Desain & Arsitektur"
                    },
                    "subclassification": {
                        "id": "6270",
                        "description": "Desain Interior"
                    }
                }
            ],
            "companyName": "PT Jensen Group Bali",
            "companyProfileStructuredDataId": 705514,
            "displayStyle": {
                "search": "A"
            },
            "displayType": "standout",
            "id": "80330739",
            "isFeatured": false,
            "listingDate": "2024-11-21T09:18:06Z",
            "listingDateDisplay": "2 hari yang lalu",
            "locations": [
                {
                    "label": "Badung, Bali",
                    "countryCode": "ID",
                    "seoHierarchy": [
                        {
                            "contextualName": "Badung Bali"
                        },
                        {
                            "contextualName": "Bali"
                        }
                    ]
                }
            ],
            "roleId": "interior-design",
            "salaryLabel": "",
            "solMetadata": {
                "searchRequestToken": "f0f542dd-ece5-452d-a708-20dc4f799947",
                "token": "0~f0f542dd-ece5-452d-a708-20dc4f799947",
                "jobId": "80330739",
                "section": "MAIN",
                "sectionRank": 1126,
                "jobAdType": "ORGANIC",
                "tags": {
                    "mordor__flights": "mordor_510",
                    "mordor__s": "1"
                }
            },
            "teaser": "PT. Jensen Group Bali, are looking for a creative, detail-oriented Design Manager to lead our design team.",
            "title": "Design Manager (for Interior Design & Architectural company)",
            "tracking": "ewogICJ0b2tlbiI6ICI1YzYyYTg1Mi01MzJmLTQ5ZmUtYmM2ZS02OGRkOWE3ZDY2MGJfNiIKfQ==",
            "workTypes": [
                "Full time"
            ],
            "workArrangements": {
                "data": [
                    {
                        "id": "1",
                        "label": {
                            "text": "Kantor"
                        }
                    }
                ]
            }
        },
        {
            "advertiser": {
                "id": "60895165",
                "description": "Saint Nicholas School"
            },
            "bulletPoints": [],
            "branding": {
                "serpLogoUrl": "https://bx-branding-gateway.cloud.seek.com.au/81575fc7-915b-458d-97c1-9a9a3a5f2000.1/serpLogo"
            },
            "classifications": [
                {
                    "classification": {
                        "id": "6123",
                        "description": "Pendidikan & Pelatihan"
                    },
                    "subclassification": {
                        "id": "6134",
                        "description": "Pengajaran – Pendidikan Menengah"
                    }
                }
            ],
            "companyName": "Saint Nicholas School",
            "companyProfileStructuredDataId": 428145,
            "displayStyle": {
                "search": "A"
            },
            "displayType": "standout",
            "id": "80203808",
            "isFeatured": false,
            "listingDate": "2024-11-15T04:19:47Z",
            "listingDateDisplay": "9 hari yang lalu",
            "locations": [
                {
                    "label": "Jakarta Utara, Jakarta Raya",
                    "countryCode": "ID",
                    "seoHierarchy": [
                        {
                            "contextualName": "Jakarta Utara Jakarta Raya"
                        },
                        {
                            "contextualName": "Jakarta Raya"
                        }
                    ]
                }
            ],
            "roleId": "information-technology-teacher",
            "salaryLabel": "",
            "solMetadata": {
                "searchRequestToken": "f0f542dd-ece5-452d-a708-20dc4f799947",
                "token": "0~f0f542dd-ece5-452d-a708-20dc4f799947",
                "jobId": "80203808",
                "section": "MAIN",
                "sectionRank": 1127,
                "jobAdType": "ORGANIC",
                "tags": {
                    "mordor__flights": "mordor_510",
                    "mordor__s": "1"
                }
            },
            "teaser": "URGENTLY REQUIRED\nSaint Nicholas School are looking for a dedicated and experienced Computer Teacher to join our teaching team, IMMEDIATELY",
            "title": "ICT (Information Communication Technologies) Teacher - URGENTLY REQUIRED",
            "tracking": "ewogICJ0b2tlbiI6ICI1YzYyYTg1Mi01MzJmLTQ5ZmUtYmM2ZS02OGRkOWE3ZDY2MGJfNyIKfQ==",
            "workTypes": [
                "Full time"
            ],
            "workArrangements": {
                "data": [
                    {
                        "id": "1",
                        "label": {
                            "text": "Kantor"
                        }
                    }
                ]
            }
        },
        {
            "advertiser": {
                "id": "60898374",
                "description": "FIBERSTAR (PT. Mega Akses Persada)"
            },
            "bulletPoints": [],
            "branding": {
                "serpLogoUrl": "https://bx-branding-gateway.cloud.seek.com.au/0bc232e4-fe4e-4e73-a5cd-d8a5748bd1bf.2/serpLogo"
            },
            "classifications": [
                {
                    "classification": {
                        "id": "6281",
                        "description": "Teknologi Informasi & Komunikasi"
                    },
                    "subclassification": {
                        "id": "6289",
                        "description": "Teknik – Jaringan"
                    }
                }
            ],
            "companyName": "Fiberstar",
            "companyProfileStructuredDataId": 432492,
            "displayType": "standard",
            "id": "80249149",
            "isFeatured": false,
            "listingDate": "2024-11-18T09:16:10Z",
            "listingDateDisplay": "5 hari yang lalu",
            "locations": [
                {
                    "label": "Palembang, Sumatera Selatan",
                    "countryCode": "ID",
                    "seoHierarchy": [
                        {
                            "contextualName": "Palembang Sumatera Selatan"
                        },
                        {
                            "contextualName": "Sumatera Selatan"
                        }
                    ]
                }
            ],
            "roleId": "maintenance-technician",
            "salaryLabel": "",
            "solMetadata": {
                "searchRequestToken": "f0f542dd-ece5-452d-a708-20dc4f799947",
                "token": "0~f0f542dd-ece5-452d-a708-20dc4f799947",
                "jobId": "80249149",
                "section": "MAIN",
                "sectionRank": 1128,
                "jobAdType": "ORGANIC",
                "tags": {
                    "mordor__flights": "mordor_510",
                    "mordor__s": "1"
                }
            },
            "teaser": "Melakukan cek fisik POP/ Site : Kebersihan ruangan dan perangkat, suhu ruangan, cek kondisi Baterai & Rectifier, dan Kwh Meter.",
            "title": "Maintenance Technician (Fiber Optic) - Palembang",
            "tracking": "ewogICJ0b2tlbiI6ICI1YzYyYTg1Mi01MzJmLTQ5ZmUtYmM2ZS02OGRkOWE3ZDY2MGJfOCIKfQ==",
            "workTypes": [
                "Full time"
            ],
            "workArrangements": {
                "data": [
                    {
                        "id": "1",
                        "label": {
                            "text": "Kantor"
                        }
                    }
                ]
            }
        },
        {
            "advertiser": {
                "id": "60300148",
                "description": "PT ECS Indo Jaya"
            },
            "bulletPoints": [],
            "branding": {
                "serpLogoUrl": "https://bx-branding-gateway.cloud.seek.com.au/5274d6d7-b62c-45f8-a1d1-2aa70a8f41a1.1/serpLogo"
            },
            "classifications": [
                {
                    "classification": {
                        "id": "6281",
                        "description": "Teknologi Informasi & Komunikasi"
                    },
                    "subclassification": {
                        "id": "6296",
                        "description": "Penjualan – Pra & Pasca"
                    }
                }
            ],
            "companyName": "ECS Indo Jaya",
            "companyProfileStructuredDataId": 426782,
            "displayStyle": {
                "search": "A"
            },
            "displayType": "standout",
            "id": "80131372",
            "isFeatured": false,
            "listingDate": "2024-11-12T09:08:57Z",
            "listingDateDisplay": "11 hari yang lalu",
            "locations": [
                {
                    "label": "Jakarta Raya",
                    "countryCode": "ID",
                    "seoHierarchy": [
                        {
                            "contextualName": "Jakarta Raya"
                        }
                    ]
                }
            ],
            "roleId": "presales-engineer",
            "salaryLabel": "",
            "solMetadata": {
                "searchRequestToken": "f0f542dd-ece5-452d-a708-20dc4f799947",
                "token": "0~f0f542dd-ece5-452d-a708-20dc4f799947",
                "jobId": "80131372",
                "section": "MAIN",
                "sectionRank": 1129,
                "jobAdType": "ORGANIC",
                "tags": {
                    "mordor__flights": "mordor_510",
                    "mordor__s": "1"
                }
            },
            "teaser": "Customer Engagement: Engage with potential clients to understand their printing needs and challenges, providing customized solutions.",
            "title": "Presales Engineer",
            "tracking": "ewogICJ0b2tlbiI6ICI1YzYyYTg1Mi01MzJmLTQ5ZmUtYmM2ZS02OGRkOWE3ZDY2MGJfOSIKfQ==",
            "workTypes": [
                "Full time"
            ],
            "workArrangements": {
                "data": [
                    {
                        "id": "1",
                        "label": {
                            "text": "Kantor"
                        }
                    }
                ]
            }
        },
        {
            "advertiser": {
                "id": "60865744",
                "description": "PT Supertone (SPC)"
            },
            "bulletPoints": [],
            "branding": {
                "serpLogoUrl": "https://bx-branding-gateway.cloud.seek.com.au/5fabacc1-7061-48b0-83c9-bb0dbef61993.2/serpLogo"
            },
            "classifications": [
                {
                    "classification": {
                        "id": "6281",
                        "description": "Teknologi Informasi & Komunikasi"
                    },
                    "subclassification": {
                        "id": "6294",
                        "description": "Manajemen & Pengembangan Produk"
                    }
                }
            ],
            "companyName": "Supertone",
            "companyProfileStructuredDataId": 437422,
            "displayType": "standard",
            "id": "80173322",
            "isFeatured": false,
            "listingDate": "2024-11-14T02:54:21Z",
            "listingDateDisplay": "10 hari yang lalu",
            "locations": [
                {
                    "label": "Jakarta Barat, Jakarta Raya",
                    "countryCode": "ID",
                    "seoHierarchy": [
                        {
                            "contextualName": "Jakarta Barat Jakarta Raya"
                        },
                        {
                            "contextualName": "Jakarta Raya"
                        }
                    ]
                }
            ],
            "roleId": "Information-Technology-Staff",
            "salaryLabel": "",
            "solMetadata": {
                "searchRequestToken": "f0f542dd-ece5-452d-a708-20dc4f799947",
                "token": "0~f0f542dd-ece5-452d-a708-20dc4f799947",
                "jobId": "80173322",
                "section": "MAIN",
                "sectionRank": 1130,
                "jobAdType": "ORGANIC",
                "tags": {
                    "mordor__flights": "mordor_510",
                    "mordor__s": "1"
                }
            },
            "teaser": "Apakah Anda suka melakukan RISET Hardware Produk teknologi terbaru di Dunia?Inginkah bekerjasama dengan perusahaan teknologi terkemuka seperti...",
            "title": "IT STAFF",
            "tracking": "ewogICJ0b2tlbiI6ICI1YzYyYTg1Mi01MzJmLTQ5ZmUtYmM2ZS02OGRkOWE3ZDY2MGJfMTAiCn0=",
            "workTypes": [
                "Full time"
            ],
            "workArrangements": {
                "data": [
                    {
                        "id": "1",
                        "label": {
                            "text": "Kantor"
                        }
                    }
                ]
            }
        },
        {
            "advertiser": {
                "id": "61130359",
                "description": "PT. GEMA PRIBUMI RAYA"
            },
            "bulletPoints": [],
            "branding": {},
            "classifications": [
                {
                    "classification": {
                        "id": "1206",
                        "description": "Konstruksi"
                    },
                    "subclassification": {
                        "id": "1387",
                        "description": "Perkiraan"
                    }
                }
            ],
            "companyProfileStructuredDataId": 0,
            "displayType": "standard",
            "id": "80145405",
            "isFeatured": false,
            "listingDate": "2024-11-13T02:23:15Z",
            "listingDateDisplay": "11 hari yang lalu",
            "locations": [
                {
                    "label": "Tangerang Selatan, Banten",
                    "countryCode": "ID",
                    "seoHierarchy": [
                        {
                            "contextualName": "Tangerang Selatan Banten"
                        },
                        {
                            "contextualName": "Banten"
                        }
                    ]
                }
            ],
            "roleId": "estimator",
            "salaryLabel": "",
            "solMetadata": {
                "searchRequestToken": "f0f542dd-ece5-452d-a708-20dc4f799947",
                "token": "0~f0f542dd-ece5-452d-a708-20dc4f799947",
                "jobId": "80145405",
                "section": "MAIN",
                "sectionRank": 1131,
                "jobAdType": "ORGANIC",
                "tags": {
                    "mordor__flights": "mordor_510",
                    "mordor__s": "1"
                }
            },
            "teaser": "BSD, Tangerang Selatan",
            "title": "Estimator",
            "tracking": "ewogICJ0b2tlbiI6ICI1YzYyYTg1Mi01MzJmLTQ5ZmUtYmM2ZS02OGRkOWE3ZDY2MGJfMTEiCn0=",
            "workTypes": [
                "Full time"
            ],
            "workArrangements": {
                "data": [
                    {
                        "id": "1",
                        "label": {
                            "text": "Kantor"
                        }
                    }
                ]
            }
        },
        {
            "advertiser": {
                "id": "60178845",
                "description": "PT. Maju Makmur Group (MMG)"
            },
            "bulletPoints": [],
            "branding": {
                "serpLogoUrl": "https://bx-branding-gateway.cloud.seek.com.au/1a8a4535-a2c0-4395-969d-56c3a0eb524d.1/serpLogo"
            },
            "classifications": [
                {
                    "classification": {
                        "id": "1200",
                        "description": "Akuntansi"
                    },
                    "subclassification": {
                        "id": "6151",
                        "description": "Akuntansi & Pelaporan Finansial"
                    }
                }
            ],
            "companyName": "Maju Makmur",
            "companyProfileStructuredDataId": 439310,
            "displayStyle": {
                "search": "A"
            },
            "displayType": "standout",
            "id": "80252528",
            "isFeatured": false,
            "listingDate": "2024-11-18T11:59:57Z",
            "listingDateDisplay": "5 hari yang lalu",
            "locations": [
                {
                    "label": "Papua",
                    "countryCode": "ID",
                    "seoHierarchy": [
                        {
                            "contextualName": "Papua"
                        }
                    ]
                }
            ],
            "roleId": "accounting-supervisor",
            "salaryLabel": "",
            "solMetadata": {
                "searchRequestToken": "f0f542dd-ece5-452d-a708-20dc4f799947",
                "token": "0~f0f542dd-ece5-452d-a708-20dc4f799947",
                "jobId": "80252528",
                "section": "MAIN",
                "sectionRank": 1132,
                "jobAdType": "ORGANIC",
                "tags": {
                    "mordor__flights": "mordor_510",
                    "mordor__s": "1"
                }
            },
            "teaser": "Kualifikasi : Pendidikan Minimal. S1 Akuntansi. Usia maksimal. 30 tahun. Mengerti System Akuntansi. Pengalaman dibidang yang sama Minimal 3 tahun.",
            "title": "Accounting Supervisor - Papua",
            "tracking": "ewogICJ0b2tlbiI6ICI1YzYyYTg1Mi01MzJmLTQ5ZmUtYmM2ZS02OGRkOWE3ZDY2MGJfMTIiCn0=",
            "workTypes": [
                "Full time"
            ],
            "workArrangements": {
                "data": [
                    {
                        "id": "1",
                        "label": {
                            "text": "Kantor"
                        }
                    }
                ]
            }
        },
        {
            "advertiser": {
                "id": "60225340",
                "description": "PT Inovasi Anak Indonesia (Parkee)"
            },
            "bulletPoints": [],
            "branding": {
                "serpLogoUrl": "https://bx-branding-gateway.cloud.seek.com.au/585275e7-6cf4-4937-b446-e28deea11d24.1/serpLogo"
            },
            "classifications": [
                {
                    "classification": {
                        "id": "1209",
                        "description": "Teknik"
                    },
                    "subclassification": {
                        "id": "6039",
                        "description": "Supervisor"
                    }
                }
            ],
            "companyName": "Anak Indonesia Innovations",
            "companyProfileStructuredDataId": 519890,
            "displayStyle": {
                "search": "A"
            },
            "displayType": "standout",
            "id": "80205104",
            "isFeatured": false,
            "listingDate": "2024-11-15T05:38:34Z",
            "listingDateDisplay": "9 hari yang lalu",
            "locations": [
                {
                    "label": "Jakarta Pusat, Jakarta Raya",
                    "countryCode": "ID",
                    "seoHierarchy": [
                        {
                            "contextualName": "Jakarta Pusat Jakarta Raya"
                        },
                        {
                            "contextualName": "Jakarta Raya"
                        }
                    ]
                }
            ],
            "roleId": "supervisor",
            "salaryLabel": "Rp 6.500.000 – Rp 8.000.000 per month",
            "solMetadata": {
                "searchRequestToken": "f0f542dd-ece5-452d-a708-20dc4f799947",
                "token": "0~f0f542dd-ece5-452d-a708-20dc4f799947",
                "jobId": "80205104",
                "section": "MAIN",
                "sectionRank": 1133,
                "jobAdType": "ORGANIC",
                "tags": {
                    "mordor__flights": "mordor_510",
                    "mordor__s": "1"
                }
            },
            "teaser": "Analyzing survey reports, long-range plans, maps and other data to design new projects",
            "title": "SPV Infrastruktur",
            "tracking": "ewogICJ0b2tlbiI6ICI1YzYyYTg1Mi01MzJmLTQ5ZmUtYmM2ZS02OGRkOWE3ZDY2MGJfMTMiCn0=",
            "workTypes": [
                "Kontrak"
            ],
            "workArrangements": {
                "data": [
                    {
                        "id": "1",
                        "label": {
                            "text": "Kantor"
                        }
                    }
                ]
            }
        },
        {
            "advertiser": {
                "id": "60191987",
                "description": "PT Bina Talenta"
            },
            "bulletPoints": [],
            "branding": {
                "serpLogoUrl": "https://bx-branding-gateway.cloud.seek.com.au/07c39646-fd73-48ea-bdd0-81575e4fbd73.2/serpLogo"
            },
            "classifications": [
                {
                    "classification": {
                        "id": "1200",
                        "description": "Akuntansi"
                    },
                    "subclassification": {
                        "id": "6151",
                        "description": "Akuntansi & Pelaporan Finansial"
                    }
                }
            ],
            "companyName": "Bina Talenta",
            "companyProfileStructuredDataId": 438994,
            "displayType": "standard",
            "id": "80267118",
            "isFeatured": false,
            "listingDate": "2024-11-19T03:48:57Z",
            "listingDateDisplay": "5 hari yang lalu",
            "locations": [
                {
                    "label": "Jakarta Raya",
                    "countryCode": "ID",
                    "seoHierarchy": [
                        {
                            "contextualName": "Jakarta Raya"
                        }
                    ]
                }
            ],
            "roleId": "finance",
            "salaryLabel": "Rp 15.000.000 – Rp 20.000.000 per month",
            "solMetadata": {
                "searchRequestToken": "f0f542dd-ece5-452d-a708-20dc4f799947",
                "token": "0~f0f542dd-ece5-452d-a708-20dc4f799947",
                "jobId": "80267118",
                "section": "MAIN",
                "sectionRank": 1134,
                "jobAdType": "ORGANIC",
                "tags": {
                    "mordor__flights": "mordor_510",
                    "mordor__s": "1"
                }
            },
            "teaser": "In this role are you are required to solve routine problems, largely through precedent and referral to general guidelines.",
            "title": "Finance Record To Reporting (R2R) Mandarin",
            "tracking": "ewogICJ0b2tlbiI6ICI1YzYyYTg1Mi01MzJmLTQ5ZmUtYmM2ZS02OGRkOWE3ZDY2MGJfMTQiCn0=",
            "workTypes": [
                "Kontrak"
            ],
            "workArrangements": {
                "data": [
                    {
                        "id": "1",
                        "label": {
                            "text": "Kantor"
                        }
                    }
                ]
            }
        },
        {
            "advertiser": {
                "id": "62773433",
                "description": "PT Lg Sinarmas Technology Solutions"
            },
            "bulletPoints": [],
            "branding": {
                "serpLogoUrl": "https://bx-branding-gateway.cloud.seek.com.au/6fdc9ecd-a398-4253-9d97-265e05b958d2.1/serpLogo"
            },
            "classifications": [
                {
                    "classification": {
                        "id": "6281",
                        "description": "Teknologi Informasi & Komunikasi"
                    },
                    "subclassification": {
                        "id": "6282",
                        "description": "Arsitek"
                    }
                }
            ],
            "companyProfileStructuredDataId": 0,
            "displayStyle": {
                "search": "A"
            },
            "displayType": "standout",
            "id": "80296370",
            "isFeatured": false,
            "listingDate": "2024-11-20T07:49:32Z",
            "listingDateDisplay": "4 hari yang lalu",
            "locations": [
                {
                    "label": "Jakarta Pusat, Jakarta Raya",
                    "countryCode": "ID",
                    "seoHierarchy": [
                        {
                            "contextualName": "Jakarta Pusat Jakarta Raya"
                        },
                        {
                            "contextualName": "Jakarta Raya"
                        }
                    ]
                }
            ],
            "roleId": "salesforce-solution-architect",
            "salaryLabel": "",
            "solMetadata": {
                "searchRequestToken": "f0f542dd-ece5-452d-a708-20dc4f799947",
                "token": "0~f0f542dd-ece5-452d-a708-20dc4f799947",
                "jobId": "80296370",
                "section": "MAIN",
                "sectionRank": 1135,
                "jobAdType": "ORGANIC",
                "tags": {
                    "mordor__flights": "mordor_510",
                    "mordor__s": "1"
                }
            },
            "teaser": "The Salesforce Solution Architect leads one or more workstreams in sophisticated enterprise customer engagements.",
            "title": "Salesforce Solution Architect",
            "tracking": "ewogICJ0b2tlbiI6ICI1YzYyYTg1Mi01MzJmLTQ5ZmUtYmM2ZS02OGRkOWE3ZDY2MGJfMTUiCn0=",
            "workTypes": [
                "Kontrak"
            ],
            "workArrangements": {
                "data": [
                    {
                        "id": "1",
                        "label": {
                            "text": "Kantor"
                        }
                    }
                ]
            }
        },
        {
            "advertiser": {
                "id": "60191960",
                "description": "PT Astra Graphia Information Technology (AGIT)"
            },
            "bulletPoints": [],
            "branding": {
                "serpLogoUrl": "https://bx-branding-gateway.cloud.seek.com.au/234f579c-02a5-4bf5-9352-8cc541e24ec4.1/serpLogo"
            },
            "classifications": [
                {
                    "classification": {
                        "id": "6281",
                        "description": "Teknologi Informasi & Komunikasi"
                    },
                    "subclassification": {
                        "id": "6287",
                        "description": "Developer/Programmer"
                    }
                }
            ],
            "companyName": "Astra Graphia",
            "companyProfileStructuredDataId": 413727,
            "displayStyle": {
                "search": "A"
            },
            "displayType": "standout",
            "id": "79938054",
            "isFeatured": false,
            "listingDate": "2024-11-04T03:34:25Z",
            "listingDateDisplay": "20 hari yang lalu",
            "locations": [
                {
                    "label": "Jakarta Raya",
                    "countryCode": "ID",
                    "seoHierarchy": [
                        {
                            "contextualName": "Jakarta Raya"
                        }
                    ]
                }
            ],
            "roleId": ".net-software-developer",
            "salaryLabel": "",
            "solMetadata": {
                "searchRequestToken": "f0f542dd-ece5-452d-a708-20dc4f799947",
                "token": "0~f0f542dd-ece5-452d-a708-20dc4f799947",
                "jobId": "79938054",
                "section": "MAIN",
                "sectionRank": 1136,
                "jobAdType": "ORGANIC",
                "tags": {
                    "mordor__flights": "mordor_510",
                    "mordor__s": "1"
                }
            },
            "teaser": ".NET Developer will be responsible for software development, utilizing .NET Core, ASP.NET MVC, and object-oriented programming principles.",
            "title": "Developer (.NET, PowerBI, Android React Native, IOS, Middleware, ect)",
            "tracking": "ewogICJ0b2tlbiI6ICI1YzYyYTg1Mi01MzJmLTQ5ZmUtYmM2ZS02OGRkOWE3ZDY2MGJfMTYiCn0=",
            "workTypes": [
                "Kontrak"
            ],
            "workArrangements": {
                "data": []
            }
        },
        {
            "advertiser": {
                "id": "60887658",
                "description": "PT Ometraco Arya Samanta"
            },
            "bulletPoints": [],
            "branding": {
                "serpLogoUrl": "https://bx-branding-gateway.cloud.seek.com.au/80d209bc-e5c9-4246-bd18-63a8b02ce5a6.2/serpLogo"
            },
            "classifications": [
                {
                    "classification": {
                        "id": "6362",
                        "description": "Penjualan"
                    },
                    "subclassification": {
                        "id": "6368",
                        "description": "Perwakilan/Konsultan Penjualan"
                    }
                }
            ],
            "companyName": "Ometraco Arya Samanta",
            "companyProfileStructuredDataId": 435637,
            "displayType": "standard",
            "id": "79194949",
            "isFeatured": false,
            "listingDate": "2024-10-29T04:13:54Z",
            "listingDateDisplay": "26 hari yang lalu",
            "locations": [
                {
                    "label": "Jakarta Barat, Jakarta Raya",
                    "countryCode": "ID",
                    "seoHierarchy": [
                        {
                            "contextualName": "Jakarta Barat Jakarta Raya"
                        },
                        {
                            "contextualName": "Jakarta Raya"
                        }
                    ]
                }
            ],
            "roleId": "sales-executive",
            "salaryLabel": "Rp 6.000.000 – Rp 7.000.000 per month",
            "solMetadata": {
                "searchRequestToken": "f0f542dd-ece5-452d-a708-20dc4f799947",
                "token": "0~f0f542dd-ece5-452d-a708-20dc4f799947",
                "jobId": "79194949",
                "section": "MAIN",
                "sectionRank": 1137,
                "jobAdType": "ORGANIC",
                "tags": {
                    "mordor__flights": "mordor_510",
                    "mordor__s": "1"
                }
            },
            "tags": [
                {
                    "type": "EXPIRES_SOON",
                    "label": "Akan segera berakhir"
                }
            ],
            "teaser": "Melakukan penjualan software horeca, mencari customer baru dan merawat customer lama.\nBersedia melakukan perjalanan dinas keluar kota",
            "title": "SPV Sales Executive",
            "tracking": "ewogICJ0b2tlbiI6ICI1YzYyYTg1Mi01MzJmLTQ5ZmUtYmM2ZS02OGRkOWE3ZDY2MGJfMTciCn0=",
            "workTypes": [
                "Full time"
            ],
            "workArrangements": {
                "data": [
                    {
                        "id": "1",
                        "label": {
                            "text": "Kantor"
                        }
                    }
                ]
            }
        },
        {
            "advertiser": {
                "id": "61586737",
                "description": "PT Bringin Jati Indah"
            },
            "bulletPoints": [],
            "branding": {
                "serpLogoUrl": "https://bx-branding-gateway.cloud.seek.com.au/b8e7e75e-e2ac-4da9-b6b3-76364aac915e.1/serpLogo"
            },
            "classifications": [
                {
                    "classification": {
                        "id": "6263",
                        "description": "Desain & Arsitektur"
                    },
                    "subclassification": {
                        "id": "6265",
                        "description": "Drafting Arsitektur"
                    }
                }
            ],
            "companyName": "Bringin Jati Indah",
            "companyProfileStructuredDataId": 668992,
            "displayStyle": {
                "search": "A"
            },
            "displayType": "standout",
            "id": "80241497",
            "isFeatured": false,
            "listingDate": "2024-11-18T04:41:42Z",
            "listingDateDisplay": "6 hari yang lalu",
            "locations": [
                {
                    "label": "Jepara, Jawa Tengah",
                    "countryCode": "ID",
                    "seoHierarchy": [
                        {
                            "contextualName": "Jepara Jawa Tengah"
                        },
                        {
                            "contextualName": "Jawa Tengah"
                        }
                    ]
                }
            ],
            "roleId": "draftperson_2",
            "salaryLabel": "",
            "solMetadata": {
                "searchRequestToken": "f0f542dd-ece5-452d-a708-20dc4f799947",
                "token": "0~f0f542dd-ece5-452d-a708-20dc4f799947",
                "jobId": "80241497",
                "section": "MAIN",
                "sectionRank": 1138,
                "jobAdType": "ORGANIC",
                "tags": {
                    "mordor__flights": "mordor_510",
                    "mordor__s": "1"
                }
            },
            "teaser": "Bergabunglah dengan kami dan jadilah bagian dari tim yang dinamis dan profesional! . Kami menantikan kehadiran Anda!\"",
            "title": "DRAFTER ( Furniture )",
            "tracking": "ewogICJ0b2tlbiI6ICI1YzYyYTg1Mi01MzJmLTQ5ZmUtYmM2ZS02OGRkOWE3ZDY2MGJfMTgiCn0=",
            "workTypes": [
                "Full time"
            ],
            "workArrangements": {
                "data": [
                    {
                        "id": "1",
                        "label": {
                            "text": "Kantor"
                        }
                    }
                ]
            }
        },
        {
            "advertiser": {
                "id": "61736731",
                "description": "Magnum Estate"
            },
            "bulletPoints": [],
            "branding": {
                "serpLogoUrl": "https://bx-branding-gateway.cloud.seek.com.au/02fead2d-df6e-4db2-85f5-151ad25f531a.1/serpLogo"
            },
            "classifications": [
                {
                    "classification": {
                        "id": "6263",
                        "description": "Desain & Arsitektur"
                    },
                    "subclassification": {
                        "id": "6265",
                        "description": "Drafting Arsitektur"
                    }
                }
            ],
            "companyName": "Magnum Estate",
            "companyProfileStructuredDataId": 705080,
            "displayStyle": {
                "search": "A"
            },
            "displayType": "standout",
            "id": "80243452",
            "isFeatured": false,
            "listingDate": "2024-11-18T06:00:43Z",
            "listingDateDisplay": "6 hari yang lalu",
            "locations": [
                {
                    "label": "Badung, Bali",
                    "countryCode": "ID",
                    "seoHierarchy": [
                        {
                            "contextualName": "Badung Bali"
                        },
                        {
                            "contextualName": "Bali"
                        }
                    ]
                }
            ],
            "roleId": "draftperson_2",
            "salaryLabel": "Rp 6.000.000 – Rp 7.000.000 per month",
            "solMetadata": {
                "searchRequestToken": "f0f542dd-ece5-452d-a708-20dc4f799947",
                "token": "0~f0f542dd-ece5-452d-a708-20dc4f799947",
                "jobId": "80243452",
                "section": "MAIN",
                "sectionRank": 1139,
                "jobAdType": "ORGANIC",
                "tags": {
                    "mordor__flights": "mordor_510",
                    "mordor__s": "1"
                }
            },
            "teaser": "Let's join us, apply now!\nLet's grow together, we want you onboard",
            "title": "Drafter",
            "tracking": "ewogICJ0b2tlbiI6ICI1YzYyYTg1Mi01MzJmLTQ5ZmUtYmM2ZS02OGRkOWE3ZDY2MGJfMTkiCn0=",
            "workTypes": [
                "Kontrak"
            ],
            "workArrangements": {
                "data": [
                    {
                        "id": "1",
                        "label": {
                            "text": "Kantor"
                        }
                    }
                ]
            }
        },
        {
            "advertiser": {
                "id": "62765873",
                "description": "CV Kopi Terbaik Nusantara"
            },
            "bulletPoints": [],
            "branding": {
                "serpLogoUrl": "https://bx-branding-gateway.cloud.seek.com.au/7a71859b-c1aa-4a90-ae63-2bba17a30bfc.2/serpLogo"
            },
            "classifications": [
                {
                    "classification": {
                        "id": "6251",
                        "description": "Administrasi & Dukungan Perkantoran"
                    },
                    "subclassification": {
                        "id": "6252",
                        "description": "Asisten Administratif"
                    }
                }
            ],
            "companyProfileStructuredDataId": 0,
            "displayType": "standard",
            "id": "80235144",
            "isFeatured": false,
            "listingDate": "2024-11-18T01:59:15Z",
            "listingDateDisplay": "6 hari yang lalu",
            "locations": [
                {
                    "label": "Semarang, Jawa Tengah",
                    "countryCode": "ID",
                    "seoHierarchy": [
                        {
                            "contextualName": "Semarang Jawa Tengah"
                        },
                        {
                            "contextualName": "Jawa Tengah"
                        }
                    ]
                }
            ],
            "roleId": "Warehouse-Administration-Officer",
            "salaryLabel": "",
            "solMetadata": {
                "searchRequestToken": "f0f542dd-ece5-452d-a708-20dc4f799947",
                "token": "0~f0f542dd-ece5-452d-a708-20dc4f799947",
                "jobId": "80235144",
                "section": "MAIN",
                "sectionRank": 1140,
                "jobAdType": "ORGANIC",
                "tags": {
                    "mordor__flights": "mordor_510",
                    "mordor__s": "1"
                }
            },
            "teaser": "Admin Gudang penempatan di Gajah Mungkur, Semarang",
            "title": "Admin Gudang",
            "tracking": "ewogICJ0b2tlbiI6ICI1YzYyYTg1Mi01MzJmLTQ5ZmUtYmM2ZS02OGRkOWE3ZDY2MGJfMjAiCn0=",
            "workTypes": [
                "Kontrak"
            ],
            "workArrangements": {
                "data": [
                    {
                        "id": "1",
                        "label": {
                            "text": "Kantor"
                        }
                    }
                ]
            }
        }
    ],
    "totalCount": 3920,
    "info": {
        "timeTaken": 49,
        "source": "JobSearch-sm",
        "experiment": "mordor_510"
    },
    "userQueryId": "API4338724991479539504",
    "sortModes": [
        {
            "isActive": true,
            "name": "Relevansi",
            "value": "KeywordRelevance"
        },
        {
            "isActive": false,
            "name": "Tanggal",
            "value": "ListedDate"
        }
    ],
    "solMetadata": {
        "requestToken": "f0f542dd-ece5-452d-a708-20dc4f799947",
        "token": "0~f0f542dd-ece5-452d-a708-20dc4f799947",
        "keywords": "software",
        "sortMode": "RELEVANCE",
        "pageSize": 20,
        "pageNumber": 57,
        "totalJobCount": 3920,
        "tags": {
            "mordor:searchMarket": "UNIFIED_ID",
            "mordor:result_count_rst": "403",
            "mordor:result_count_vec": "1",
            "mordor:rt": "28",
            "mordor_vs:retrieved_count": "38101",
            "mordor:count_vec": "1",
            "mordor__flights": "mordor_510",
            "mordor__rbo_perfMng_p95_k20": "0.658",
            "mordor:count_rst": "407",
            "mordor:count_ir": "3519",
            "mordor:result_count_ir": "3516"
        }
    },
    "facets": {},
    "searchParams": {
        "sitekey": "ID-Main",
        "sourcesystem": "houston",
        "userid": "d89afcc9-eee2-4c71-842e-b6b56c89c5f6",
        "usersessionid": "d89afcc9-eee2-4c71-842e-b6b56c89c5f6",
        "eventcapturesessionid": "d89afcc9-eee2-4c71-842e-b6b56c89c5f6",
        "page": "57",
        "seekselectallpages": "true",
        "keywords": "software",
        "include": "seodata",
        "locale": "id-ID",
        "solid": "93c36c71-ca29-412a-b367-5d4d9b596c5b"
    }
}